quakephase/__init__.py
quakephase/load_MLmodel.py
quakephase/pfinput.py
quakephase/qkp_apply.py
quakephase/qkprocessing.py
quakephase/quakephase.py
quakephase/streamprocess.py
quakephase/utilplot.py
quakephase/xpick.py
quakephase/xprob.py
quakephase-0.2.5.dist-info/LICENSE
quakephase-0.2.5.dist-info/METADATA
quakephase-0.2.5.dist-info/WHEEL
quakephase-0.2.5.dist-info/top_level.txt
quakephase-0.2.5.dist-info/RECORD
